{
  "cities": [
    {
      "cityName": "Berlin",
      "country": "Germany",
      "emoji": "🇩🇪",
      "date": "2027-02-12T09:24:11.863Z",
      "notes": "Amazing 😃",
      "position": {
        "lat": 52.53586782505711,
        "lng": 13.376933665713324
      },
      "id": 98443197
    },
    {
      "cityName": "Vienna",
      "country": "Austria",
      "emoji": "🇦🇹",
      "date": "2023-10-21T22:56:44.868Z",
      "notes": "",
      "position": {
        "lat": "48.151428143221224",
        "lng": "16.391601562500004"
      },
      "id": 98443200
    },
    {
      "cityName": "Milan",
      "country": "Italy",
      "emoji": "🇮🇹",
      "date": "2023-10-21T22:56:44.868Z",
      "notes": "",
      "position": {
        "lat": "45.521743896993634",
        "lng": "9.42626953125"
      },
      "id": 98443201
    },
    {
      "cityName": "Tirana",
      "country": "Albania",
      "emoji": "🇦🇱",
      "date": "2023-10-21T23:38:46.019Z",
      "notes": "",
      "position": {
        "lat": "41.29431726315258",
        "lng": "19.863281250000004"
      },
      "id": 98443202
    },
    {
      "cityName": "Lukavica",
      "country": "Bosnia and Herzegovina",
      "emoji": "🇧🇦",
      "date": "2023-10-21T23:40:16.858Z",
      "notes": "",
      "position": {
        "lat": "43.81867485545323",
        "lng": "18.424072265625004"
      },
      "id": 98443204
    },
    {
      "cityName": "Corfu",
      "country": "Greece",
      "emoji": "🇬🇷",
      "date": "2023-10-22T08:57:11.027Z",
      "notes": "",
      "position": {
        "lat": "39.592990390285024",
        "lng": "19.9237060546875"
      },
      "id": 98443205
    },
    {
      "cityName": "Malta",
      "country": "Malta",
      "emoji": "🇲🇹",
      "date": "2023-10-22T08:57:22.291Z",
      "notes": "",
      "position": {
        "lat": "35.889050079360935",
        "lng": "14.304199218750002"
      },
      "id": 98443206
    }
  ]
}